XenValidator/__init__.py
XenValidator/schema.py
XenValidator/validators.py
XenValidator-0.2.7.dist-info/METADATA
XenValidator-0.2.7.dist-info/WHEEL
XenValidator-0.2.7.dist-info/top_level.txt
XenValidator-0.2.7.dist-info/RECORD
