Metadata-Version: 2.1
Name: XenValidator
Version: 0.2.7
Summary: XenValidator is schema validation library for Python, You can Validate Strings, Numbers, Objects, Arrays, Dates, URLs, Ip addresses, regexes & more. You can even create your custom validators & use picks validator to validate a custom string value!
Home-page: https://github.com/XenigmaAi/XenValidator
Author: Xenigma
Author-email: helpworkagents@gmail.com
Classifier: Programming Language :: Python :: 3
Classifier: License :: OSI Approved :: MIT License
Classifier: Operating System :: OS Independent
Requires-Python: >=3.6
